eventor/__init__.py
eventor/api.py
eventor/schemas.py
eventor_api-0.1.0.dist-info/METADATA
eventor_api-0.1.0.dist-info/WHEEL
eventor_api-0.1.0.dist-info/top_level.txt
eventor_api-0.1.0.dist-info/RECORD
